[
  {
    "url" : "./assets/images/animation/0048194.jpg-c_215_290_x-f_jpg-q_x-xxyxx.jpg",
    "name" : "Le voyage de Lila",
    "date" : "2004",
    "genre" : "animation"
  },
  {
    "url" : "./assets/images/animation/003422.jpg-c_215_290_x-f_jpg-q_x-xxyxx.jpg",
    "name" : "Sahara",
    "date" : "2018",
    "genre" : "animation"
  },
  {
    "url" : "./assets/images/animation/0056825.jpg-c_215_290_x-f_jpg-q_x-xxyxx.jpg",
    "name" : "Coco",
    "date" : "2014",
    "genre" : "animation"
  },
  {
    "url" : "./assets/images/animation/0323277.jpg-c_215_290_x-f_jpg-q_x-xxyxx.jpg",
    "name" : "Pat et Mat",
    "date" : "2014",
    "genre" : "animation"
  },
  {
    "url" : "./assets/images/animation/0323902.jpg-c_215_290_x-f_jpg-q_x-xxyxx.jpg",
    "name" : "Les Indestructibles 2",
    "date" : "2012",
    "genre" : "animation"
  },
  {
    "url" : "./assets/images/animation/0841317.jpg-c_215_290_x-f_jpg-q_x-xxyxx.jpg",
    "name" : "Parvana",
    "date" : "2005",
    "genre" : "animation"
  },
  {
    "url" : "./assets/images/animation/1052693.jpg-c_215_290_x-f_jpg-q_x-xxyxx.jpg",
    "name" : "Pierre lapin",
    "date" : "2017",
    "genre" : "animation"
  },
  {
    "url" : "./assets/images/animation/1504983.jpg-c_215_290_x-f_jpg-q_x-xxyxx.jpg",
    "name" : "Hotel Transylvanie 3",
    "date" : "2018",
    "genre" : "animation"
  },
  {
    "url" : "./assets/images/animation/1622249.jpg-c_215_290_x-f_jpg-q_x-xxyxx.jpg",
    "name" : "Tad",
    "date" : "2018",
    "genre" : "animation"
  },
  {
    "url" : "./assets/images/animation/1748397.jpg-c_215_290_x-f_jpg-q_x-xxyxx.jpg",
    "name" : "Spider-Man",
    "date" : "2018",
    "genre" : "animation"
  },
  {
    "url" : "./assets/images/animation/3087565.jpg-c_215_290_x-f_jpg-q_x-xxyxx.jpg",
    "name" : "Capitaine Morten",
    "date" : "2016",
    "genre" : "animation"
  },
  {
    "url" : "./assets/images/animation/4019182.jpg-c_215_290_x-f_jpg-q_x-xxyxx.jpg",
    "name" : "L'île aux chiens'",
    "date" : "2018",
    "genre" : "animation"
  },
  {
    "url" : "./assets/images/animation/4241392.jpg-c_215_290_x-f_jpg-q_x-xxyxx.jpg",
    "name" : "Léo et les extraterrestres",
    "date" : "2017",
    "genre" : "animation"
  },
  {
    "url" : "./assets/images/animation/5068927.jpg-c_215_290_x-f_jpg-q_x-xxyxx.jpg",
    "name" : "mon voisin Totoro",
    "date" : "1998",
    "genre" : "animation"
  },
  {
    "url" : "./assets/images/animation/5440157.jpg-c_215_290_x-f_jpg-q_x-xxyxx.jpg",
    "name" : "Dragon 3",
    "date" : "2014",
    "genre" : "animation"
  },
  {
    "url" : "./assets/images/animation/5771427.jpg-c_215_290_x-f_jpg-q_x-xxyxx.jpg",
    "name" : "Mutafukaz",
    "date" : "2010",
    "genre" : "animation"
  },
  {
    "url" : "./assets/images/animation/1760452.jpg-c_215_290_x-f_jpg-q_x-xxyxx.jpg",
    "name" : "Have a nice day",
    "date" : "2017",
    "genre" : "animation"
  },
  {
    "url" : "./assets/images/animation/2694666.jpg-c_215_290_x-f_jpg-q_x-xxyxx.jpg",
    "name" : "Ralph 2.0",
    "date" : "2016",
    "genre" : "animation"
  }
]
